urlbreakdown.py
urlbreakdown-0.1.1.dist-info/LICENSE
urlbreakdown-0.1.1.dist-info/METADATA
urlbreakdown-0.1.1.dist-info/WHEEL
urlbreakdown-0.1.1.dist-info/top_level.txt
urlbreakdown-0.1.1.dist-info/RECORD
