Metadata-Version: 2.1
Name: urlbreakdown
Version: 0.1.1
Summary: splits a URL into individual components, unescapes arguments, and performs light calculations for manual or automated analysis
Home-page: https://github.com/bonifield/URLBreakdown
Author: James Bonifield
Author-email: bonifield.tools@gmail.com
License: UNKNOWN
Platform: UNKNOWN
Classifier: Programming Language :: Python :: 3
Classifier: License :: OSI Approved :: MIT License
Classifier: Operating System :: OS Independent
